odoo/addons/stock_location_children/README.rst
odoo/addons/stock_location_children/__init__.py
odoo/addons/stock_location_children/__manifest__.py
odoo/addons/stock_location_children/i18n/it.po
odoo/addons/stock_location_children/i18n/stock_location_children.pot
odoo/addons/stock_location_children/models/__init__.py
odoo/addons/stock_location_children/models/stock_location.py
odoo/addons/stock_location_children/readme/CONTRIBUTORS.rst
odoo/addons/stock_location_children/readme/DESCRIPTION.rst
odoo/addons/stock_location_children/static/description/icon.png
odoo/addons/stock_location_children/static/description/index.html
odoo/addons/stock_location_children/tests/__init__.py
odoo/addons/stock_location_children/tests/test_stock_location_children.py
odoo14_addon_stock_location_children-14.0.1.0.1.dev7.dist-info/METADATA
odoo14_addon_stock_location_children-14.0.1.0.1.dev7.dist-info/WHEEL
odoo14_addon_stock_location_children-14.0.1.0.1.dev7.dist-info/top_level.txt
odoo14_addon_stock_location_children-14.0.1.0.1.dev7.dist-info/RECORD
